fastboot/__init__.py
fastboot/fastboot.py
fastboot/flask_app.py
fastboot/provider.py
fastboot/annotations/__init__.py
fastboot/annotations/component.py
fastboot/annotations/inject.py
fastboot/annotations/service.py
fastboot/dependency_container/__init__.py
fastboot/dependency_container/component_registry.py
fastboot/dependency_container/container.py
fastboot/dependency_container/controller_registry.py
fastboot/dependency_container/dependency_registry.py
fastboot/dependency_container/registry.py
fastboot/utils/__init__.py
fastboot/utils/sort.py
fastboot/web/__init__.py
fastboot/web/delete.py
fastboot/web/get.py
fastboot/web/post.py
fastboot/web/put.py
fastboot/web/rest_controller.py
fastboot-0.0.3.dist-info/LICENSE.txt
fastboot-0.0.3.dist-info/METADATA
fastboot-0.0.3.dist-info/WHEEL
fastboot-0.0.3.dist-info/top_level.txt
fastboot-0.0.3.dist-info/RECORD
